autotrader_crawler/__init__.py
autotrader_crawler/crawler.py
test/__init__.py
test/sample.py
test/test_crawler.py
autotrader_crawler-0.4.dist-info/LICENSE
autotrader_crawler-0.4.dist-info/METADATA
autotrader_crawler-0.4.dist-info/WHEEL
autotrader_crawler-0.4.dist-info/top_level.txt
autotrader_crawler-0.4.dist-info/RECORD
