Metadata-Version: 2.1
Name: autotrader-crawler
Version: 0.4
Summary: A package to assist in crawling Autotrader results
Home-page: https://gitlab.com/autotrader-crawler/autotrader-crawler
Author: Mark Slater
Author-email: mark.slater@mail.com
License: UNKNOWN
Platform: UNKNOWN
Classifier: Development Status :: 4 - Beta
Classifier: Programming Language :: Python :: 3
Classifier: License :: OSI Approved :: Apache Software License
Classifier: Operating System :: OS Independent
Requires-Python: >=3.6
